palettes/Dracula.npz
palettes/Dracula.txt
palettes/Grayscale.npz
palettes/Grayscale.txt
palettes/Gruvbox.npz
palettes/Gruvbox.txt
palettes/One_Dark.npz
palettes/One_Dark.txt
palettes/__init__.py
palettes/Catppuccin/Frappe.npz
palettes/Catppuccin/Frappe.txt
palettes/Catppuccin/Latte.npz
palettes/Catppuccin/Latte.txt
palettes/Catppuccin/Macchiato.npz
palettes/Catppuccin/Macchiato.txt
palettes/Catppuccin/Mocha.npz
palettes/Catppuccin/Mocha.txt
palettes/Nord/Aurora.npz
palettes/Nord/Aurora.txt
palettes/Nord/Frost.npz
palettes/Nord/Frost.txt
palettes/Nord/Polar_Night.npz
palettes/Nord/Polar_Night.txt
palettes/Nord/Snow_Storm.npz
palettes/Nord/Snow_Storm.txt
palettipy/__init__.py
palettipy/color.py
palettipy/config.py
palettipy/palette.py
palettipy/palettes_loader.py
palettipy/tests/__init__.py
palettipy/tests/test_color.py
palettipy/tests/test_image.png
palettipy/tests/test_palette.npz
palettipy/tests/test_palette.py
palettipy/tests/test_palette.txt
palettipy/tests/test_palette_ignored.md
palettipy/tests/test_palette_noncached.txt
palettipy/tests/test_palette_wrong_1.txt
palettipy/tests/test_palette_wrong_2.txt
palettipy/tests/test_palettes_loader.py
palettipy/tests/test_palettipy.py
palettipy/tests/test_palette/variant.txt
palettipy-0.0.1.dist-info/LICENSE
palettipy-0.0.1.dist-info/METADATA
palettipy-0.0.1.dist-info/WHEEL
palettipy-0.0.1.dist-info/top_level.txt
palettipy-0.0.1.dist-info/RECORD
