Metadata-Version: 2.1
Name: palettipy
Version: 0.0.1
Summary: Match the colors of an image to a palette
Author-email: Roberto Coratti <corattiroberto@gmail.com>
License: MIT License
Keywords: color,palette,image,colorscheme,colors,color-scheme,image-processing,palettes,palettes-files,palettes-colors
Classifier: Programming Language :: Python :: 3.10
Classifier: Programming Language :: Python :: 3.11
Classifier: License :: OSI Approved :: MIT License
Classifier: Intended Audience :: Developers
Classifier: Operating System :: OS Independent
Classifier: Topic :: Multimedia
Classifier: Typing :: Typed
Requires-Python: >=3.10
License-File: LICENSE
Requires-Dist: numpy (>=1.23.4)
Requires-Dist: Pillow (>=9.3.0)
Provides-Extra: dev
Requires-Dist: black ; extra == 'dev'
Requires-Dist: pre-commit ; extra == 'dev'
Requires-Dist: pytest ; extra == 'dev'
Requires-Dist: coverage ; extra == 'dev'
Requires-Dist: pytest-cov ; extra == 'dev'
Requires-Dist: coveralls ; extra == 'dev'
